{
  "_hero.jpg": {
    "title": "Erhai Lake Dali 01.JPG",
    "author": "Brücke-Osteuropa",
    "source": "https://commons.wikimedia.org/wiki/File%3AErhai%20Lake%20Dali%2001.JPG",
    "license": "Public domain",
    "license_url": "",
    "alt": "Erhai - Lake of Dali (Yunnan)",
    "status": "needs-review"
  },
  "dali-old-town-center.jpg": {
    "title": "1 dali old town yunnan 2012b.jpg",
    "author": "chensiyuan",
    "source": "https://commons.wikimedia.org/wiki/File%3A1%20dali%20old%20town%20yunnan%202012b.jpg",
    "license": "CC BY-SA 4.0",
    "license_url": "https://creativecommons.org/licenses/by-sa/4.0",
    "alt": "dali old town yunnan china night 2012 yang ren jie",
    "status": "needs-review"
  },
  "xizhou-old-town.jpg": {
    "title": "Xizhou town square gate.JPG",
    "author": "Chris DeLacy",
    "source": "https://commons.wikimedia.org/wiki/File%3AXizhou%20town%20square%20gate.JPG",
    "license": "CC0",
    "license_url": "http://creativecommons.org/publicdomain/zero/1.0/deed.en",
    "alt": "An entrance gate to Xizhou's town square (四方街)",
    "status": "needs-review"
  },
  "shaping-monday-market.jpg": {
    "title": "1 dali old town yunnan 2012b.jpg",
    "author": "chensiyuan",
    "source": "https://commons.wikimedia.org/wiki/File%3A1%20dali%20old%20town%20yunnan%202012b.jpg",
    "license": "CC BY-SA 4.0",
    "license_url": "https://creativecommons.org/licenses/by-sa/4.0",
    "alt": "dali old town yunnan china night 2012 yang ren jie",
    "status": "needs-review"
  },
  "three-pagodas-chongsheng-temple.jpg": {
    "title": "Three Pagodas of Chongsheng Temple front view from entrance.jpg",
    "author": "Jason Zhang",
    "source": "https://commons.wikimedia.org/wiki/File%3AThree%20Pagodas%20of%20Chongsheng%20Temple%20front%20view%20from%20entrance.jpg",
    "license": "CC BY-SA 3.0",
    "license_url": "https://creativecommons.org/licenses/by-sa/3.0",
    "alt": "A front view of the Three Pagodas of Chongsheng Temple in Dali, Yunnan. This was taken in the entrance area.",
    "status": "needs-review"
  },
  "dali-old-town-evening-walk.jpg": {
    "title": "大建旁村本主庙-大殿 2024-08-20 01.jpg",
    "author": "Kcx36",
    "source": "https://commons.wikimedia.org/wiki/File%3A%E5%A4%A7%E5%BB%BA%E6%97%81%E6%9D%91%E6%9C%AC%E4%B8%BB%E5%BA%99-%E5%A4%A7%E6%AE%BF%202024-08-20%2001.jpg",
    "license": "CC BY-SA 4.0",
    "license_url": "https://creativecommons.org/licenses/by-sa/4.0",
    "alt": "​大建旁村本主庙",
    "status": "needs-review"
  },
  "erhai-lake-boat-trip.jpg": {
    "title": "NDL-DC 1301465-Utagawa Kunisada-鵜飼船御遊-嘉永5-cmb.jpg",
    "author": "Utagawa Kunisada",
    "source": "https://commons.wikimedia.org/wiki/File%3ANDL-DC%201301465-Utagawa%20Kunisada-%E9%B5%9C%E9%A3%BC%E8%88%B9%E5%BE%A1%E9%81%8A-%E5%98%89%E6%B0%B85-cmb.jpg",
    "license": "Public domain",
    "license_url": "",
    "alt": "from the picture album \"Azuma Nishiki-e shū\"",
    "status": "needs-review"
  },
  "dali-museum-and-catholic-cathedral.jpg": {
    "title": "1 songzanlin 2018a.jpg",
    "author": "Chensiyuan",
    "source": "https://commons.wikimedia.org/wiki/File%3A1%20songzanlin%202018a.jpg",
    "license": "CC BY-SA 4.0",
    "license_url": "https://creativecommons.org/licenses/by-sa/4.0",
    "alt": "songzanlin monastery yunnan",
    "status": "needs-review"
  },
  "xinghua-village-restaurant.jpg": {
    "title": "Greater Bay Area Rail Transit Network.png",
    "author": "Picrazy2",
    "source": "https://commons.wikimedia.org/wiki/File%3AGreater%20Bay%20Area%20Rail%20Transit%20Network.png",
    "license": "CC BY-SA 4.0",
    "license_url": "https://creativecommons.org/licenses/by-sa/4.0",
    "alt": "Guangdong-Hong Kong-Macau Bay Area transit network (Pearl River Delta Metro Region), including high speed, higher-speed,",
    "status": "needs-review"
  },
  "golden-flower-bai-cuisine.jpg": {
    "title": "云南省大剧院 2025-09-17.jpg",
    "author": "Kcx36",
    "source": "https://commons.wikimedia.org/wiki/File%3A%E4%BA%91%E5%8D%97%E7%9C%81%E5%A4%A7%E5%89%A7%E9%99%A2%202025-09-17.jpg",
    "license": "CC BY-SA 4.0",
    "license_url": "https://creativecommons.org/licenses/by-sa/4.0",
    "alt": "​云南省大剧院",
    "status": "needs-review"
  },
  "xizhou-baba-vendors.jpg": {
    "title": "Xizhou town square gate.JPG",
    "author": "Chris DeLacy",
    "source": "https://commons.wikimedia.org/wiki/File%3AXizhou%20town%20square%20gate.JPG",
    "license": "CC0",
    "license_url": "http://creativecommons.org/publicdomain/zero/1.0/deed.en",
    "alt": "An entrance gate to Xizhou's town square (四方街)",
    "status": "needs-review"
  },
  "a-peng-bbq.jpg": {
    "title": "チャーシューメン（松食堂）.jpg",
    "author": "くろふね",
    "source": "https://commons.wikimedia.org/wiki/File%3A%E3%83%81%E3%83%A3%E3%83%BC%E3%82%B7%E3%83%A5%E3%83%BC%E3%83%A1%E3%83%B3%EF%BC%88%E6%9D%BE%E9%A3%9F%E5%A0%82%EF%BC%89.jpg",
    "license": "CC BY-SA 4.0",
    "license_url": "https://creativecommons.org/licenses/by-sa/4.0",
    "alt": "福島県喜多方市、松食堂、チャーシューメン、ラーメン",
    "status": "needs-review"
  }
}
